examples/__init__.py
examples/basic_usage.py
examples/mcp_server_example.py
seedream_mcp/__init__.py
seedream_mcp/client.py
seedream_mcp/config.py
seedream_mcp/server.py
seedream_mcp/sse_server.py
seedream_mcp/tools/__init__.py
seedream_mcp/tools/browse_images.py
seedream_mcp/tools/image_to_image.py
seedream_mcp/tools/multi_image_fusion.py
seedream_mcp/tools/sequential_generation.py
seedream_mcp/tools/text_to_image.py
seedream_mcp/utils/__init__.py
seedream_mcp/utils/auto_save.py
seedream_mcp/utils/download_manager.py
seedream_mcp/utils/errors.py
seedream_mcp/utils/file_manager.py
seedream_mcp/utils/logging.py
seedream_mcp/utils/path_utils.py
seedream_mcp/utils/user_guide.py
seedream_mcp/utils/validation.py
seedream_mcp-1.0.1.dist-info/licenses/LICENSE
seedream_mcp-1.0.1.dist-info/METADATA
seedream_mcp-1.0.1.dist-info/WHEEL
seedream_mcp-1.0.1.dist-info/entry_points.txt
seedream_mcp-1.0.1.dist-info/top_level.txt
seedream_mcp-1.0.1.dist-info/RECORD
