Metadata-Version: 2.4
Name: seedream-mcp
Version: 1.0.1
Summary: 基于火山引擎Seedream 4.0 API的MCP工具，支持AI图像生成功能
Home-page: https://github.com/tengmmvp/seedream-mcp
Author: Seedream MCP Team
Author-email: tengmmvp@qq.com
Classifier: Development Status :: 4 - Beta
Classifier: Intended Audience :: Developers
Classifier: License :: OSI Approved :: MIT License
Classifier: Operating System :: OS Independent
Classifier: Programming Language :: Python :: 3
Classifier: Programming Language :: Python :: 3.8
Classifier: Programming Language :: Python :: 3.9
Classifier: Programming Language :: Python :: 3.10
Classifier: Programming Language :: Python :: 3.11
Classifier: Programming Language :: Python :: 3.12
Classifier: Topic :: Software Development :: Libraries :: Python Modules
Classifier: Topic :: Scientific/Engineering :: Artificial Intelligence
Classifier: Topic :: Multimedia :: Graphics
Requires-Python: >=3.8
License-File: LICENSE
Requires-Dist: mcp>=1.0.0
Requires-Dist: pydantic>=2.0.0
Requires-Dist: typing-extensions>=4.0.0
Requires-Dist: volcengine-python-sdk[ark]>=1.0.0
Requires-Dist: aiohttp>=3.8.0
Requires-Dist: aiofiles>=23.0.0
Requires-Dist: python-dotenv>=1.0.0
Requires-Dist: loguru>=0.7.0
Requires-Dist: Pillow>=10.0.0
Dynamic: author
Dynamic: author-email
Dynamic: classifier
Dynamic: description
Dynamic: description-content-type
Dynamic: home-page
Dynamic: license-file
Dynamic: requires-dist
Dynamic: requires-python
Dynamic: summary
